{
  "headers": {
    "content-length": "3858",
    "x-amz-id-2": "EmXBB3zqFJ1Z0IEUcVf6uTSGMuld+EuVyyhMpwkzNoiFFCw3jikacPoUOH8PzaAA8279mtG5U2o=",
    "x-amz-version-id": "9Hirj3bOhyaMU9rCC9CUt0Dk7m8MIaVm",
    "etag": "\"5d1b36e90b1e5819abf6dac989ea5644\"",
    "x-amz-request-id": "JD0541J58X7KSE42",
    "server": "deploy/us-east4-c",
    "access-control-allow-origin": "*",
    "cache-control": "public, max-age=31536000, immutable",
    "date": "Thu, 10 Mar 2022 20:46:21 GMT",
    "content-type": "application/javascript",
    "last-modified": "Thu, 10 Mar 2022 08:23:01 GMT"
  },
  "url": "https://deno.land/std@0.129.0/node/_crypto/crypto_browserify/browserify_aes/modes/mod.js",
  "now": {
    "secs_since_epoch": 1646945180,
    "nanos_since_epoch": 570553000
  }
}