{
  "headers": {
    "x-amz-version-id": "EqL9brhPfNWZQmeFo43xI6TadKuREQPc",
    "date": "Thu, 10 Mar 2022 20:46:20 GMT",
    "cache-control": "public, max-age=31536000, immutable",
    "server": "deploy/us-east4-c",
    "content-length": "1982",
    "x-amz-request-id": "NHFFRRMBED6G2GTN",
    "access-control-allow-origin": "*",
    "etag": "\"c2c0a51099403711f5d728dbc7d1eb99\"",
    "last-modified": "Tue, 08 Jun 2021 19:16:56 GMT",
    "x-amz-id-2": "aPFWho0H18BV2bT06aBXKgCwIqYunHLW1EyGPltCtMf8kuMOrC8mvE6Jm3XZ9xTO6h6y1gBYbDE=",
    "content-type": "application/typescript; charset=utf-8"
  },
  "url": "https://deno.land/std@0.98.0/async/mux_async_iterator.ts",
  "now": {
    "secs_since_epoch": 1646945179,
    "nanos_since_epoch": 720699000
  }
}