{
  "headers": {
    "x-amz-request-id": "NHFBD48AZYCZ3ZA8",
    "date": "Thu, 10 Mar 2022 20:46:20 GMT",
    "content-length": "1192",
    "etag": "\"1f1c0bc522651e5fe0bb23cb309ba924\"",
    "access-control-allow-origin": "*",
    "x-amz-id-2": "hCnmpHUNgHCDXqRk79x6QwgwfQdJtocFEiN3xVit5wnA6b0lkUN5r7j4fD8CQHd6IsF4cvp76sw=",
    "x-amz-version-id": "Tb7vnP0k1HKWrP0dPs0wufX9DFGkplxP",
    "last-modified": "Thu, 10 Mar 2022 08:23:03 GMT",
    "server": "deploy/us-east4-c",
    "content-type": "application/typescript; charset=utf-8",
    "cache-control": "public, max-age=31536000, immutable"
  },
  "url": "https://deno.land/std@0.129.0/path/common.ts",
  "now": {
    "secs_since_epoch": 1646945179,
    "nanos_since_epoch": 585595000
  }
}