{
  "headers": {
    "date": "Thu, 10 Mar 2022 20:46:20 GMT",
    "content-type": "application/javascript",
    "last-modified": "Thu, 10 Mar 2022 08:23:02 GMT",
    "etag": "\"2718134937024deeb6ac0239ccf16ec9\"",
    "content-length": "581",
    "x-amz-version-id": "hMbVNomyYSZ7vx22PouIE2W2yAJ7qnfP",
    "access-control-allow-origin": "*",
    "server": "deploy/us-east4-c",
    "cache-control": "public, max-age=31536000, immutable",
    "x-amz-request-id": "NHF65HD8CWH3WKMJ",
    "x-amz-id-2": "Cb4N3BjbZ+6oTd+45rD+xp7uhR5R7SYNgCKxpFborF1LvUHU2/7id+eYH/ZYGYDENK3+qngVnhg="
  },
  "url": "https://deno.land/std@0.129.0/node/_crypto/crypto_browserify/public_encrypt/mgf.js",
  "now": {
    "secs_since_epoch": 1646945180,
    "nanos_since_epoch": 29548000
  }
}