{
  "headers": {
    "access-control-allow-origin": "*",
    "x-amz-id-2": "aaG5sIymhsj88COrknM2i9V1owQYj8GzMkEFi5e1TO18yqbItQLxK5I/D2Rq6MxIk/QbTWivUy4=",
    "date": "Thu, 10 Mar 2022 20:46:21 GMT",
    "last-modified": "Thu, 10 Mar 2022 08:23:03 GMT",
    "cache-control": "public, max-age=31536000, immutable",
    "content-length": "5621",
    "x-amz-request-id": "JD018PN7DK3GG25Z",
    "x-amz-version-id": "8dQs5DM5LKhYKL483PEbo5gBPamzURLp",
    "etag": "\"acf2572e4aa59df1ad96aca90710d160\"",
    "content-type": "application/typescript; charset=utf-8",
    "server": "deploy/us-east4-c"
  },
  "url": "https://deno.land/std@0.129.0/node/internal_binding/types.ts",
  "now": {
    "secs_since_epoch": 1646945180,
    "nanos_since_epoch": 198176000
  }
}