{
  "headers": {
    "date": "Thu, 10 Mar 2022 20:46:21 GMT",
    "cache-control": "public, max-age=31536000, immutable",
    "content-length": "618",
    "content-type": "application/typescript; charset=utf-8",
    "x-amz-request-id": "JD0FMBJ1E1Y2KRPD",
    "access-control-allow-origin": "*",
    "x-amz-id-2": "RlwBF39FuQHK6Yzjky/tBlFVzRA93M/zInP2JZqZuDIZptIqGMt12X4Tywsxq0Xzjn9ROcERQck=",
    "last-modified": "Thu, 10 Mar 2022 08:23:00 GMT",
    "server": "deploy/us-east4-c",
    "etag": "\"15c6952b6a9b987fd0230b929ef7077f\"",
    "x-amz-version-id": "86Nk8f9g.QcTKPk_E0a0kz7Q4aYWFPCU"
  },
  "url": "https://deno.land/std@0.129.0/async/deadline.ts",
  "now": {
    "secs_since_epoch": 1646945180,
    "nanos_since_epoch": 781771000
  }
}